inspect.py
setup.py
micropython_inspect.egg-info/PKG-INFO
micropython_inspect.egg-info/SOURCES.txt
micropython_inspect.egg-info/dependency_links.txt
micropython_inspect.egg-info/top_level.txt