Metadata-Version: 1.0
Name: micropython-inspect
Version: 0.1.1
Summary: inspect module for MicroPython
Home-page: https://github.com/micropython/micropython/issues/405
Author: MicroPython Developers
Author-email: micro-python@googlegroups.com
License: MIT
Platform: UNKNOWN
